[
	{
				"name": "Sükh",
		        "value": "40",
		        "PSI": "4/5/3 wwbbrr 1",
		        "CBT": "7/9/6 wwwwbr 2,3",
		        "VIG": "4/5/4 wwwbbr 4,5",
		        "RAP": "5/6/3 wwwbbrr 6",
				"socle": "40mm",
	},
	{
				"name": "Alagh",
		        "value": "35",
		        "PSI": "4/5/2 wwbbr 1",
		        "CBT": "6/7/4 wwbbrr 2,3",
		        "VIG": "4/6/3 wwwbrr 4,5",
		        "RAP": "4/6/3 wbbbrr 6",
				"socle": "40mm",
	},
	{
				"name": "Odval",
		        "value": "40",
		        "PSI": "4/5/2 wwbrr 1",
		        "CBT": "7/9/6 wwwwbr 2,3",
		        "VIG": "4/5/4 wwwbbr 4,5",
		        "RAP": "5/6/3 wwwbbrr 6",
				"socle": "40mm",
	},
	{
				"name": "Sükh",
		        "value": "40",
		        "PSI": "4/5/3 wwbbrr 1",
		        "CBT": "7/9/6 wwwwbr 2,3",
		        "VIG": "4/5/4 wwwbbr 4,5",
		        "RAP": "5/6/3 wwwbbrr 6",
				"socle": "40mm",
	},
	{
				"name": "Sükh",
		        "value": "40",
		        "PSI": "4/5/3 wwbbrr 1",
		        "CBT": "7/9/6 wwwwbr 2,3",
		        "VIG": "4/5/4 wwwbbr 4,5",
		        "RAP": "5/6/3 wwwbbrr 6",
				"socle": "40mm",
	},
	{
				"name": "Sükh",
		        "value": "40",
		        "PSI": "4/5/3 wwbbrr 1",
		        "CBT": "7/9/6 wwwwbr 2,3",
		        "VIG": "4/5/4 wwwbbr 4,5",
		        "RAP": "5/6/3 wwwbbrr 6",
				"socle": "40mm",
	},
	{
				"name": "Sükh",
		        "value": "40",
		        "PSI": "4/5/3 wwbbrr 1",
		        "CBT": "7/9/6 wwwwbr 2,3",
		        "VIG": "4/5/4 wwwbbr 4,5",
		        "RAP": "5/6/3 wwwbbrr 6",
				"socle": "40mm",
	},
	{
				"name": "Sükh",
		        "value": "40",
		        "PSI": "4/5/3 wwbbrr 1",
		        "CBT": "7/9/6 wwwwbr 2,3",
		        "VIG": "4/5/4 wwwbbr 4,5",
		        "RAP": "5/6/3 wwwbbrr 6",
				"socle": "40mm",
	},
]